llama_index/py.typed
llama_index/vector_stores/myscale/__init__.py
llama_index/vector_stores/myscale/base.py
llama_index_vector_stores_myscale-0.3.0.dist-info/METADATA
llama_index_vector_stores_myscale-0.3.0.dist-info/WHEEL
llama_index_vector_stores_myscale-0.3.0.dist-info/RECORD
